{"title":"The Non-Central Model","markdown":{"headingText":"The Non-Central Model","containsRefs":false,"markdown":"\nA natural starting point is to construct the process by applying squaring a \nGaussian random field. This is analogous to the log-Gaussian \nCox process, where the exponential transformation is used, and will result in \nthe marginal distribution of the intensity field being exactly a Chi-square distribution.\n\n## Definition\n\nMotivated by this, we consider the model\n\n$$\n\\Lambda(u) = Z(u)^2,\n$$\n\nwhere $Z(u)$ is a Gaussian random field (GRF) defined on a spatial domain \n$W \\subset \\mathbb{R}^2$.\n\nNotice that at each location $u$, the intensity is given by the square of a \nGaussian random variable, and hence follows a (scaled?) non-central chi-square \ndistribution with one degree of freedom.\n\nConditional on $\\Lambda(\\cdot)$, the point process $X$ is an inhomogeneous \nPoisson process with intensity function $\\Lambda(u)$.\n\nThe Gaussian random field $Z(u)$ is characterised by its mean function\n\n$$\nm(u) = \\mathbb{E}[Z(u)]\n$$\n\nand covariance function\n\n$$\nC(u,v) = \\mathrm{Cov}(Z(u), Z(v)),\n$$\n\nfor $u, v \\in W$.\n\nIn many cases, it is convenient to express dependence using the correlation function\n\n$$\n\\rho(u, v) = \n\\frac{C(u,v)}{\\sqrt{C(u,u)}\\sqrt{C(v,v)}}.\n$$\n\n## First-order intensity\n\nWe have seen previously, that for any Cox process, the first order intensity\nhas the form\n\n$$\n\\lambda(u) = \\mathbb{E}[\\Lambda(u)]\n$$\n\nSo we have\n\n$$\n\\begin{align}\n\\lambda(u) &= \\mathbb{E}[\\Lambda(u)]\\\\\n&= \\mathbb{E}[Z(u)^2]\\\\\n&= \\mathrm{Var}(Z(u)) + \\mathbb{E}[Z(u)]^2\\\\\n&= C(u,u) + m(u)^2\n\\end{align}\n$$\n\n## Second-order intensity\n\nWe have also seen that for any Cox process, the second-order intensity can be\nfound as\n\n$$\n\\begin{align}\n\\lambda^{(2)}(u, v) &= \\mathbb{E}[\\Lambda(u) \\Lambda(v)]\n\\end{align}\n$$\n\nApplying the Gaussian 4th moment identity, we arrive at \n\n$$\n\\begin{align}\n\\lambda^{(2)}(u, v) &= \\mathbb{E}[\\Lambda(u) \\Lambda(v)]\\\\\n&= \\mathbb{E}[Z(u)^2 Z(v)^2]\\\\\n&= (C(u, u) + m(u)^2)(C(v, v) + m(v)^2) + 2 C(u, v)^2 + 4 m(u) m(v) C(u, v)\\\\\n&= \\lambda(u)\\lambda(v) + 2 C(u, v)^2 + 4 m(u) m(v) C(u, v)\n\\end{align}\n$$\n\n::: {.callout-note collapse=\"true\"}\n### Proof of the Gaussian 4th moment identity\n\nNeed to add proof.\n\nLet $(X, Y)$ be bivariate normal with,\n\n$$\n\\begin{align*}\n&\\mu_X = \\mathbb{E}[X],\\qquad \\mu_Y = \\mathbb{E}[Y],\\\\\n&\\sigma_X^2 = \\text{Var}(X),\\quad \\sigma_Y^2 = \\text{Var}(Y)\\\\\n&\\sigma_{XY} = \\text{Cov}(X, Y)\n\\end{align*}\n$$\n\nThen\n\n$$\n\\mathbb{E}[X^2 Y^2] = (\\sigma_X^2 + \\mu_X^2)(\\sigma_Y^2 + \\mu_Y^2) \n+ 2\\sigma_{XY}^2 + 4\\mu_X\\mu_Y\\sigma_{XY}\n$$\n:::\n\nThe first term corresponds to the baseline Poisson component, while the remaining \nterms capture clustering induced by the covariance structure of the underlying field. \nIn particular, the quadratic term $2 C(u,v)^2$\nreflects purely second-order dependence, while the linear term \n$4 m(u)m(v)C(u,v)$ arises from interaction between the mean and covariance structure.\n\nIt is immediately obvious if there is no covariance between $Z(u)$ and $Z(v)$\n(i.e. $C(u, v) = 0$), that the second order structure is simply the \nfirst-order intensity ($\\lambda(u)\\lambda(v)$), consistent with CSR.\n\n::: {.callout-note collapse=\"true\"}\n## Alternative derivation of second-order intensity\n\nEasier way (??? doesn't really seem that much easier), using the identity:\n\n$$\n\\mathbb{E}[AB] = \\mathrm{Cov}(A,B) + \\mathbb{E}[A]\\mathbb{E}[B]\n$$\n\nwith $A=\\Lambda(u)$ and $B=\\Lambda(v)$, which gives\n \n$$\n\\lambda^{(2)}(u,v)\n=\n\\mathbb{E}[\\Lambda(u)\\Lambda(v)]\n=\n\\mathrm{Cov}(\\Lambda(u),\\Lambda(v))\n+\n\\lambda(u)\\lambda(v)\n$$\n \nSo then we just need to compute $\\mathrm{Cov}(\\Lambda(u),\\Lambda(v))$. And since\n\n$$\n\\Lambda(u)=\\sum_{i=1}^k Z_i(u)^2, \\qquad \\Lambda(v)=\\sum_{j=1}^k Z_j(v)^2,\n$$\n \nbiliniearity of covariance gives\n \n$$\n\\mathrm{Cov}(\\Lambda(u),\\Lambda(v))\n=\n\\sum_{i=1}^k\\sum_{j=1}^k\n\\mathrm{Cov}(Z_i(u)^2,Z_j(v)^2).\n$$\n\n...Continues on\n\n:::\n\n## PCF\n\nThe PCF follows directly from the above derivations:\n\n$$\n\\begin{align}\ng(u, v) &= \\frac{\\lambda^{(2)}(u, v)}{\\lambda(u)\\lambda(v)}\\\\\n&= \\frac{\\lambda(u)\\lambda(v) + 2 C(u, v)^2 + 4 m(u) m(v) C(u, v)}{\\lambda(u)\\lambda(v)}\\\\\n&= 1 + \\frac{2 C(u, v)^2 + 4 m(u) m(v) C(u, v)}{\\lambda(u)\\lambda(v)}\\\\\n\\end{align}\n$$\n\nIt is immediately apparent from the form of the PCF, that the *mean* of the GRF\n$Z(u)$ has a direct effect on the clustering behavior of the process.\n\nIn contrast to the LGCP, where clustering is driven solely by the covariance \nstructure of the underlying field, the mean of the GRF here directly influences \nthe clustering behaviour.\n\n## K-function\n\n[To be added.]\n\n## Stationary and isotropic case\n\nIn many practical settings, it is natural to assume that the underlying Gaussian \nrandom field is stationary and isotropic. In this case:\n\n- the mean is constant:\n\n$$\nm(u) = m\n$$\n\n- the variance is constant:\n\n$$\nC(u,u) = \\sigma^2\n$$\n\n- the covariance only depends on distance:\n\n$$\nC(u, v) = C(r) = \\sigma^2 \\rho(r), \\quad r = \\|u - v\\|\n$$\n\nUnder these assumptions, we have first-order intensity\n\n$$\n\\lambda(u) = \\lambda = \\sigma^2 + m^2,\n$$\n\nand PCF\n\n$$\n\\begin{align}\ng(r) &= 1 + \\frac{2C(r)^2 + 4m^2C(r)}{(\\sigma^2 + m^2)^2}\\\\ \n&= 1 + \\frac{2\\sigma^4\\rho(r)^2 + 4m^2\\sigma^2\\rho(r)}{(\\sigma^2 + m^2)^2}\n\\end{align}\n$$\n\nThis expression reveals that the pair correlation function is composed of both \na quadratic term in $\\rho(r)$ and a linear term in $\\rho(r)$, in contrast to the \ncentered case considered later.\n\n## Thoughts on this construction\n\nWhile the non-central construction provides a valid and flexible model, the \nresulting expressions for the second-order structure are somewhat difficult to \ninterpret. In particular, the pair correlation function contains both linear and \nquadratic terms in the correlation function $\\rho(r)$, arising from interaction \nbetween the mean and covariance structure of the underlying field.\n\nThis complicates interpretation, as it is not immediately clear how changes in \nthe mean function $m(u)$ and covariance function $C(u,v)$ separately influence \nthe clustering behaviour of the process. Moreover, the presence of mixed terms \nmakes it difficult to isolate the contribution of second-order dependence alone.\n\nFor these reasons, it is natural to consider a simplified version of the model \nin which the Gaussian random field is centered, ($m(u) = 0$). As we will see, \nthis leads to a significantly cleaner and more interpretable form of the \nsecond-order structure.\n\n\n\n\n\n\n\n\n\n\n\n\n\n\n\n\n\n\n\n","srcMarkdownNoYaml":""},"formats":{"html":{"identifier":{"display-name":"HTML","target-format":"html","base-format":"html"},"execute":{"fig-width":7,"fig-height":5,"fig-format":"retina","fig-dpi":96,"df-print":"default","error":false,"eval":true,"cache":null,"freeze":false,"echo":true,"output":true,"warning":true,"include":true,"keep-md":false,"keep-ipynb":false,"ipynb":null,"enabled":null,"daemon":null,"daemon-restart":false,"debug":false,"ipynb-filters":[],"ipynb-shell-interactivity":null,"plotly-connected":true,"engine":"markdown"},"render":{"keep-tex":false,"keep-typ":false,"keep-source":false,"keep-hidden":false,"prefer-html":false,"output-divs":true,"output-ext":"html","fig-align":"default","fig-pos":null,"fig-env":null,"code-fold":"none","code-overflow":"scroll","code-link":false,"code-line-numbers":false,"code-tools":false,"tbl-colwidths":"auto","merge-includes":true,"inline-includes":false,"preserve-yaml":false,"latex-auto-mk":true,"latex-auto-install":true,"latex-clean":true,"latex-min-runs":1,"latex-max-runs":10,"latex-makeindex":"makeindex","latex-makeindex-opts":[],"latex-tlmgr-opts":[],"latex-input-paths":[],"latex-output-dir":null,"link-external-icon":false,"link-external-newwindow":false,"self-contained-math":false,"format-resources":[],"notebook-links":true},"pandoc":{"standalone":true,"wrap":"none","default-image-extension":"png","to":"html","css":["../styles.css"],"output-file":"cscp_definition.html"},"language":{"toc-title-document":"Table of contents","toc-title-website":"On this page","related-formats-title":"Other Formats","related-notebooks-title":"Notebooks","source-notebooks-prefix":"Source","other-links-title":"Other Links","code-links-title":"Code Links","launch-dev-container-title":"Launch Dev Container","launch-binder-title":"Launch Binder","article-notebook-label":"Article Notebook","notebook-preview-download":"Download Notebook","notebook-preview-download-src":"Download Source","notebook-preview-back":"Back to Article","manuscript-meca-bundle":"MECA Bundle","section-title-abstract":"Abstract","section-title-appendices":"Appendices","section-title-footnotes":"Footnotes","section-title-references":"References","section-title-reuse":"Reuse","section-title-copyright":"Copyright","section-title-citation":"Citation","appendix-attribution-cite-as":"For attribution, please cite this work as:","appendix-attribution-bibtex":"BibTeX citation:","appendix-view-license":"View License","title-block-author-single":"Author","title-block-author-plural":"Authors","title-block-affiliation-single":"Affiliation","title-block-affiliation-plural":"Affiliations","title-block-published":"Published","title-block-modified":"Modified","title-block-keywords":"Keywords","callout-tip-title":"Tip","callout-note-title":"Note","callout-warning-title":"Warning","callout-important-title":"Important","callout-caution-title":"Caution","code-summary":"Code","code-tools-menu-caption":"Code","code-tools-show-all-code":"Show All Code","code-tools-hide-all-code":"Hide All Code","code-tools-view-source":"View Source","code-tools-source-code":"Source Code","tools-share":"Share","tools-download":"Download","code-line":"Line","code-lines":"Lines","copy-button-tooltip":"Copy to Clipboard","copy-button-tooltip-success":"Copied!","repo-action-links-edit":"Edit this page","repo-action-links-source":"View source","repo-action-links-issue":"Report an issue","back-to-top":"Back to top","search-no-results-text":"No results","search-matching-documents-text":"matching documents","search-copy-link-title":"Copy link to search","search-hide-matches-text":"Hide additional matches","search-more-match-text":"more match in this document","search-more-matches-text":"more matches in this document","search-clear-button-title":"Clear","search-text-placeholder":"","search-detached-cancel-button-title":"Cancel","search-submit-button-title":"Submit","search-label":"Search","toggle-section":"Toggle section","toggle-sidebar":"Toggle sidebar navigation","toggle-dark-mode":"Toggle dark mode","toggle-reader-mode":"Toggle reader mode","toggle-navigation":"Toggle navigation","crossref-fig-title":"Figure","crossref-tbl-title":"Table","crossref-lst-title":"Listing","crossref-thm-title":"Theorem","crossref-lem-title":"Lemma","crossref-cor-title":"Corollary","crossref-prp-title":"Proposition","crossref-cnj-title":"Conjecture","crossref-def-title":"Definition","crossref-exm-title":"Example","crossref-exr-title":"Exercise","crossref-ch-prefix":"Chapter","crossref-apx-prefix":"Appendix","crossref-sec-prefix":"Section","crossref-eq-prefix":"Equation","crossref-lof-title":"List of Figures","crossref-lot-title":"List of Tables","crossref-lol-title":"List of Listings","environment-proof-title":"Proof","environment-remark-title":"Remark","environment-solution-title":"Solution","listing-page-order-by":"Order By","listing-page-order-by-default":"Default","listing-page-order-by-date-asc":"Oldest","listing-page-order-by-date-desc":"Newest","listing-page-order-by-number-desc":"High to Low","listing-page-order-by-number-asc":"Low to High","listing-page-field-date":"Date","listing-page-field-title":"Title","listing-page-field-description":"Description","listing-page-field-author":"Author","listing-page-field-filename":"File Name","listing-page-field-filemodified":"Modified","listing-page-field-subtitle":"Subtitle","listing-page-field-readingtime":"Reading Time","listing-page-field-wordcount":"Word Count","listing-page-field-categories":"Categories","listing-page-minutes-compact":"{0} min","listing-page-category-all":"All","listing-page-no-matches":"No matching items","listing-page-words":"{0} words","listing-page-filter":"Filter","draft":"Draft"},"metadata":{"lang":"en","fig-responsive":true,"quarto-version":"1.7.27","theme":["cosmo","brand"]},"extensions":{"book":{"multiFile":true}}}},"projectFormats":["html"]}